<?xml version="1.0" encoding="UTF-8"?>
<!DOCTYPE mapper PUBLIC "-//mybatis.org//DTD Mapper 3.0//EN" "http://mybatis.org/dtd/mybatis-3-mapper.dtd">
<mapper namespace="bouquet.infrastructure.datasource.autogen.inventories.ArrivalLineMapper">
    <resultMap id="BaseResultMap" type="bouquet.domain.model.autogen.inventories.ArrivalLine">
        <!--
          WARNING - @mbg.generated
          This element is automatically generated by MyBatis Generator, do not modify.
        -->
        <id column="arrival_number" jdbcType="INTEGER" property="arrivalNumber"/>
        <id column="arrival_line_number" jdbcType="INTEGER" property="arrivalLineNumber"/>
        <result column="product_number" jdbcType="INTEGER" property="productNumber"/>
        <result column="product_name" jdbcType="VARCHAR" property="productName"/>
        <result column="supplier_number" jdbcType="INTEGER" property="supplierNumber"/>
        <result column="supplier_line_number" jdbcType="INTEGER" property="supplierLineNumber"/>
        <result column="quantity" jdbcType="INTEGER" property="quantity"/>
        <result column="created_by" jdbcType="VARCHAR" property="createdBy"/>
        <result column="created_at" jdbcType="TIMESTAMP" property="createdAt"/>
    </resultMap>
    <sql id="Base_Column_List">
        <!--
          WARNING - @mbg.generated
          This element is automatically generated by MyBatis Generator, do not modify.
        -->
        arrival_number, arrival_line_number, product_number, product_name, supplier_number,
        supplier_line_number, quantity, created_by, created_at
    </sql>
    <insert id="insertSelective" parameterType="bouquet.domain.model.autogen.inventories.ArrivalLine">
        <!--
          WARNING - @mbg.generated
          This element is automatically generated by MyBatis Generator, do not modify.
        -->
        insert into inventories.arrival_line
        <trim prefix="(" suffix=")" suffixOverrides=",">
            <if test="arrivalNumber != null">
                arrival_number,
            </if>
            <if test="arrivalLineNumber != null">
                arrival_line_number,
            </if>
            <if test="productNumber != null">
                product_number,
            </if>
            <if test="productName != null">
                product_name,
            </if>
            <if test="supplierNumber != null">
                supplier_number,
            </if>
            <if test="supplierLineNumber != null">
                supplier_line_number,
            </if>
            <if test="quantity != null">
                quantity,
            </if>
            <if test="createdBy != null">
                created_by,
            </if>
            <if test="createdAt != null">
                created_at,
            </if>
        </trim>
        <trim prefix="values (" suffix=")" suffixOverrides=",">
            <if test="arrivalNumber != null">
                #{arrivalNumber,jdbcType=INTEGER},
            </if>
            <if test="arrivalLineNumber != null">
                #{arrivalLineNumber,jdbcType=INTEGER},
            </if>
            <if test="productNumber != null">
                #{productNumber,jdbcType=INTEGER},
            </if>
            <if test="productName != null">
                #{productName,jdbcType=VARCHAR},
            </if>
            <if test="supplierNumber != null">
                #{supplierNumber,jdbcType=INTEGER},
            </if>
            <if test="supplierLineNumber != null">
                #{supplierLineNumber,jdbcType=INTEGER},
            </if>
            <if test="quantity != null">
                #{quantity,jdbcType=INTEGER},
            </if>
            <if test="createdBy != null">
                #{createdBy,jdbcType=VARCHAR},
            </if>
            <if test="createdAt != null">
                #{createdAt,jdbcType=TIMESTAMP},
            </if>
        </trim>
    </insert>
    <update id="updateByPrimaryKeySelective" parameterType="bouquet.domain.model.autogen.inventories.ArrivalLine">
        <!--
          WARNING - @mbg.generated
          This element is automatically generated by MyBatis Generator, do not modify.
        -->
        update inventories.arrival_line
        <set>
            <if test="productNumber != null">
                product_number = #{productNumber,jdbcType=INTEGER},
            </if>
            <if test="productName != null">
                product_name = #{productName,jdbcType=VARCHAR},
            </if>
            <if test="supplierNumber != null">
                supplier_number = #{supplierNumber,jdbcType=INTEGER},
            </if>
            <if test="supplierLineNumber != null">
                supplier_line_number = #{supplierLineNumber,jdbcType=INTEGER},
            </if>
            <if test="quantity != null">
                quantity = #{quantity,jdbcType=INTEGER},
            </if>
            <if test="createdBy != null">
                created_by = #{createdBy,jdbcType=VARCHAR},
            </if>
            <if test="createdAt != null">
                created_at = #{createdAt,jdbcType=TIMESTAMP},
            </if>
        </set>
        where arrival_number = #{arrivalNumber,jdbcType=INTEGER}
        and arrival_line_number = #{arrivalLineNumber,jdbcType=INTEGER}
    </update>
</mapper>
